{"1": ["R Br Bl' Br' R' L' U Bl U' Bl' L Bl", "Br' U F' L F' Bl F Bl' L' F U Br", "Bl' Br Bl L R U' Br' U Br R' Br' L'", "Br L R Br' U' Br U R' L' Bl' Br' Bl", "Br' U' F' L Bl F' Bl' F L' F U' Br", "Bl' L' Bl U Bl' U' L R Br Bl Br' R'"], "2": ["Br' Bl' R U R' Br R U' R' Br' Bl Br", "R' L F L' R U' R' L F L' R", "Bl' Br L Bl' L' Bl Br' Bl' L Bl L' Bl", "Bl F Br R' F' R Br' R' F R F' Bl'", "F L F R' U' R F' R' U R L' F'", "F Bl F' R' U' R F R' U Bl' R F'", "F' Br' L U L' F L U' L' F' Br F", "Bl Br Bl' L' U' L Bl L' U Br' L Bl'", "Br' F' L F L' Bl' L F' L' Bl F Br", "Br Bl F L' Bl' L F' L' Bl L Bl' Br'", "F Br L U L U' Br' U L' U' L' F'", "L R' F R L' U' L R' F R L'", "Bl' Br' R Br R' F' R Br' R' F Br Bl", "Bl' F R' Br' L' U Br U' L R F' Bl"], "3": ["Bl' Br' F' R Br R' F R Br' R' Br Bl", "R' L F' L' R U R' L F' L' R", "Bl F R' F' R Br R' F R Br' F' Bl'", "F L U L U' Br U L' U' Br' L' F'", "F L R' U' R F R' U R F' L' F'", "L R' F' R L' U L R' F' R L'", "Bl Br L' U' L Bl' L' U L Bl Br' Bl'", "Br Bl L' Bl' L F L' Bl L F' Bl' Br'", "F Bl R' U' R F' R' U R F Bl' F'", "Bl' L Bl' L' Bl Br Bl' L Bl Br' L' Bl", "Bl' F R' L' U Br' U' Br L R F' Bl", "F' Br' F L U L' F' L U' Br L' F", "Br' F' Bl' L F L' Bl L F' L' F Br", "Br' Bl' Br R U R' Br' R U' Bl R' Br"], "4": ["R Br' R L R' Br R L' R", "R' F L F' L' Bl' L F L' Bl F' R", "R Br' L' R L' R' Br R L R' L R'", "L R' L R L' F L R' L' R F' L'", "L' R L' R L Bl L' R' L Bl' R' L", "L R' L Bl L' R L Bl' L", "L' U' L' F' L' F' R' F' R' U' R'", "R' F' L R' L' R F R' L R L' R", "L F' Br R' F R Br' R' F' R F L'"], "5": ["L F' R' F R Br R' F' R Br' F L'", "L' Bl R L' R L Bl' L' R' L R' L", "L' Bl L' R' L Bl' L' R L'", "R' L R' Br' R L' R' Br R'", "R L' R L' R' Br' R L R' Br L R'", "R' F Bl' L F' L' Bl L F L' F' R", "L F R' L R L' F' L R' L' R L'", "R U R F R F L F L U L", "R' L R' L' R F' R' L R L' F R"]}